setup.py
phonetic_matcher/__init__.py
phonetic_matcher/metaphone.py
phonetic_matcher/phonemes.py
phonetic_matcher/string_matching.py
phonetic_matcher.egg-info/PKG-INFO
phonetic_matcher.egg-info/SOURCES.txt
phonetic_matcher.egg-info/dependency_links.txt
phonetic_matcher.egg-info/requires.txt
phonetic_matcher.egg-info/top_level.txt