Metadata-Version: 1.0
Name: phonetic-matcher
Version: 0.1.1
Summary: matching strings by phonetics
Home-page: https://github.com/OpenJarbas/phonetic_matcherpyth
Author: jarbasAi
Author-email: jarbasai@mailfence.com
License: Apache-2.0
Platform: UNKNOWN
